tabfairgan/__init__.py
tabfairgan/main.py
tabfairgan/modules.py
tabfairgan/utils.py
tabfairgan-0.1.0.dist-info/LICENSE
tabfairgan-0.1.0.dist-info/METADATA
tabfairgan-0.1.0.dist-info/WHEEL
tabfairgan-0.1.0.dist-info/top_level.txt
tabfairgan-0.1.0.dist-info/RECORD
