Metadata-Version: 2.1
Name: tabfairgan
Version: 0.1.0
Summary: A GAN-based approach for fairness-aware synthetic data generation
Home-page: https://github.com/amirarsalan90/TabFairGAN
Author: Amirarsalan Rajabi
Classifier: Programming Language :: Python :: 3
Classifier: License :: OSI Approved :: MIT License
Classifier: Operating System :: OS Independent
Requires-Python: >=3.10
License-File: LICENSE
Requires-Dist: pandas
Requires-Dist: numpy
Requires-Dist: scikit-learn
Requires-Dist: tqdm
